autora/theorist/bms/__init__.py
autora/theorist/bms/fit_prior.py
autora/theorist/bms/mcmc.py
autora/theorist/bms/parallel.py
autora/theorist/bms/prior.py
autora/theorist/bms/regressor.py
autora/theorist/bms/utils.py
autora_theorist_bms-1.0.6.dist-info/LICENSE
autora_theorist_bms-1.0.6.dist-info/METADATA
autora_theorist_bms-1.0.6.dist-info/WHEEL
autora_theorist_bms-1.0.6.dist-info/top_level.txt
autora_theorist_bms-1.0.6.dist-info/RECORD
