Metadata-Version: 2.1
Name: autora-theorist-bms
Version: 1.0.6
Summary: Bayesian Machine Scientist theorist for AutoRA
Author-email: Joshua Hewson <joshua_hewson@brown.edu>
License: MIT License
Project-URL: homepage, http://www.empiricalresearch.ai
Project-URL: repository, https://github.com/AutoResearch/autora-theorist-bms
Project-URL: documentation, https://autoresearch.github.io/autora/
Requires-Python: <4,>=3.8
Provides-Extra: dev
License-File: LICENSE
